qrev_logex/__init__.py
qrev_logex/logex.py
qrev_logex-0.1.0.dist-info/METADATA
qrev_logex-0.1.0.dist-info/WHEEL
qrev_logex-0.1.0.dist-info/RECORD
