Metadata-Version: 2.1
Name: qrev-logex
Version: 0.1.0
Summary: 
Author: leeparnell
Author-email: 152523161+leeparnell@users.noreply.github.com
Requires-Python: >=3.11,<4.0
Classifier: Programming Language :: Python :: 3
Classifier: Programming Language :: Python :: 3.11
Classifier: Programming Language :: Python :: 3.12
